README.rst
setup.cfg
setup.py
on/__init__.py
on.caroufredsel.egg-info/PKG-INFO
on.caroufredsel.egg-info/SOURCES.txt
on.caroufredsel.egg-info/dependency_links.txt
on.caroufredsel.egg-info/entry_points.txt
on.caroufredsel.egg-info/namespace_packages.txt
on.caroufredsel.egg-info/not-zip-safe
on.caroufredsel.egg-info/paster_plugins.txt
on.caroufredsel.egg-info/requires.txt
on.caroufredsel.egg-info/top_level.txt
on/caroufredsel/__init__.py
on/caroufredsel/testing.py
on/caroufredsel/tests/__init__.py
on/caroufredsel/tests/test_installation.py