Metadata-Version: 1.1
Name: on.caroufredsel
Version: 0.1
Summary: Shim to load Caroufredsel as a resource
Home-page: https://github.com/muellert/on.caroufredsel.git
Author: Toni Mueller
Author-email: support@oeko.net
License: MIT + GPL
Keywords: Caroufredsel
Platform: UNKNOWN
Classifier: Framework :: Plone
Classifier: Framework :: Plone :: 4.2
Classifier: Framework :: Plone :: 4.3
Classifier: Programming Language :: Python
Classifier: Programming Language :: JavaScript
